virtualpp/__init__.py
virtualpp/final.py
virtualpp-0.0.7.dist-info/LICENSE
virtualpp-0.0.7.dist-info/METADATA
virtualpp-0.0.7.dist-info/WHEEL
virtualpp-0.0.7.dist-info/top_level.txt
virtualpp-0.0.7.dist-info/RECORD
