Metadata-Version: 2.1
Name: virtualpp
Version: 0.0.7
Summary: An opencv based virtual pingpong
Home-page: https://github.com/abhijithneilabraham/PINGPONG-hand
Author: Abhijith Neil Abraham
Author-email: abhijithneilabrahampk@gmail.com
License: UNKNOWN
Platform: UNKNOWN
Classifier: Programming Language :: Python :: 3
Classifier: License :: OSI Approved :: MIT License
Classifier: Operating System :: OS Independent
